{
    "name": "TripletMarginLoss",
    "category": "Module",
    "path": "torch.nn.TripletMarginLoss",
    "init_arguments": {
        "margin": {
            "required": "False",
            "default": 1.0
        },
        "p": {
            "required": "False",
            "default": 2.0
        },
        "eps": {
            "required": "False",
            "default": 1e-06
        },
        "swap": {
            "required": "False",
            "default": false
        },
        "size_average": {
            "required": "False",
            "default": null
        },
        "reduce": {
            "required": "False",
            "default": null
        },
        "reduction": {
            "required": "False",
            "default": "mean"
        }
    },
    "forward_arguments": {
        "anchor": {
            "type": "Tensor",
            "required": "True",
            "default": null
        },
        "positive": {
            "type": "Tensor",
            "required": "True",
            "default": null
        },
        "negative": {
            "type": "Tensor",
            "required": "True",
            "default": null
        }
    },
    "output": [
        "output"
    ]
}
